global_temperature/__init__.py
global_temperature/config.py
global_temperature/config.yaml
global_temperature/errors.py
global_temperature/grids/01x01/data.parquet
global_temperature/grids/03x03/data.parquet
global_temperature/grids/grid.py
global_temperature/temperature.py
global_temperature/temperature_base.py
global_temperature/temperature_monthly.py
global_temperature/tools/download.py
global_temperature/tools/validate.py
global_temperature-0.1.7.dist-info/METADATA
global_temperature-0.1.7.dist-info/WHEEL
global_temperature-0.1.7.dist-info/licenses/LICENSE
global_temperature-0.1.7.dist-info/RECORD
