Metadata-Version: 2.4
Name: global-temperature
Version: 0.1.7
Summary: provide global monthly temperature data from 1950 to present
License-Expression: MIT
License-File: LICENSE
Author: zacwang
Author-email: zacwang15@gmail.com
Requires-Python: >=3.10
Classifier: Programming Language :: Python :: 3
Classifier: Programming Language :: Python :: 3.10
Classifier: Programming Language :: Python :: 3.11
Classifier: Programming Language :: Python :: 3.12
Classifier: Programming Language :: Python :: 3.13
Classifier: Programming Language :: Python :: 3.14
Requires-Dist: numpy (>=2.2.4,<3.0.0)
Requires-Dist: pandas (>=2.2.3,<3.0.0)
Requires-Dist: pandera[pandas] (>=0.23.1,<0.24.0)
Requires-Dist: pyarrow (>=19.0.1,<20.0.0)
Requires-Dist: pygeohash (>=3.0.1,<4.0.0)
Requires-Dist: pyyaml (>=6.0.2,<7.0.0)
Requires-Dist: requests (>=2.32.3,<3.0.0)
Requires-Dist: scipy (>=1.15.2,<2.0.0)
Project-URL: homepage, https://github.com/ZacWang15/global-temperature
Project-URL: repository, https://github.com/ZacWang15/global-temperature
